bed2idt/__init__.py
bed2idt/config.py
bed2idt/main.py
bed2idt-1.3.0.dist-info/METADATA
bed2idt-1.3.0.dist-info/WHEEL
bed2idt-1.3.0.dist-info/entry_points.txt
bed2idt-1.3.0.dist-info/licenses/LICENSE
bed2idt-1.3.0.dist-info/RECORD
