Metadata-Version: 2.4
Name: bed2idt
Version: 1.3.0
Summary: Converts primer.bed files to IDT ordering templates
Author-email: ChrisKent <chrisgkent@gmail.com>
License-Expression: BSD-3-Clause
License-File: LICENSE
Requires-Python: >=3.10
Requires-Dist: primalbedtools>=0.10.1
Requires-Dist: typer>=0.16.1
Requires-Dist: xlsxwriter<4,>=3.1.2
